{
  "db_name": "PostgreSQL",
  "query": "\n            SELECT \n                (SELECT count(*) FROM resume_uploads WHERE job_id = $1 AND status NOT IN ('completed', 'failed')) +\n                (SELECT count(*) FROM project_uploads WHERE job_id = $1 AND status NOT IN ('completed', 'failed'))\n            as count\n            ",
  "describe": {
    "columns": [
      {
        "ordinal": 0,
        "name": "count",
        "type_info": "Int8"
      }
    ],
    "parameters": {
      "Left": [
        "Uuid"
      ]
    },
    "nullable": [
      null
    ]
  },
  "hash": "104f06f79ce5ac575174abcc7b2b8733229540b3af92a66849fbfce0a3020fc6"
}
